odoo/addons/sale_report_country_state/README.rst
odoo/addons/sale_report_country_state/__init__.py
odoo/addons/sale_report_country_state/__manifest__.py
odoo/addons/sale_report_country_state/i18n/es.po
odoo/addons/sale_report_country_state/i18n/it.po
odoo/addons/sale_report_country_state/i18n/sale_report_country_state.pot
odoo/addons/sale_report_country_state/readme/CONTRIBUTORS.rst
odoo/addons/sale_report_country_state/readme/DESCRIPTION.rst
odoo/addons/sale_report_country_state/readme/USAGE.rst
odoo/addons/sale_report_country_state/reports/__init__.py
odoo/addons/sale_report_country_state/reports/sale_report.py
odoo/addons/sale_report_country_state/reports/sale_report_views.xml
odoo/addons/sale_report_country_state/static/description/icon.png
odoo/addons/sale_report_country_state/static/description/index.html
odoo_addon_sale_report_country_state-16.0.1.0.0.5.dist-info/METADATA
odoo_addon_sale_report_country_state-16.0.1.0.0.5.dist-info/WHEEL
odoo_addon_sale_report_country_state-16.0.1.0.0.5.dist-info/top_level.txt
odoo_addon_sale_report_country_state-16.0.1.0.0.5.dist-info/RECORD
